dragonk8s/__init__.py
dragonk8s/cmd/__init__.py
dragonk8s/cmd/replicaset_controller.py
dragonk8s/dragon/__init__.py
dragonk8s/dragon/api_client.py
dragonk8s/dragon/configuration.py
dragonk8s/dragon/exceptions.py
dragonk8s/dragon/rest.py
dragonk8s/dragon/api/__init__.py
dragonk8s/dragon/models/__init__.py
dragonk8s/dragon/models/io_dragon_apps_v1_job.py
dragonk8s/dragon/models/io_dragon_apps_v1_job_list.py
dragonk8s/dragon/models/io_dragon_apps_v1_job_spec.py
dragonk8s/dragon/models/io_dragon_apps_v1_job_spec_selector.py
dragonk8s/dragon/models/io_dragon_apps_v1_job_spec_selector_match_expressions.py
dragonk8s/dragon/models/io_dragon_apps_v1_job_spec_template.py
dragonk8s/dragon/models/io_dragon_apps_v1_job_spec_template_spec.py
dragonk8s/dragon/models/io_dragon_apps_v1_job_spec_template_spec_affinity.py
dragonk8s/dragon/models/io_dragon_apps_v1_job_spec_template_spec_affinity_node_affinity.py
dragonk8s/dragon/models/io_dragon_apps_v1_job_spec_template_spec_affinity_node_affinity_preference.py
dragonk8s/dragon/models/io_dragon_apps_v1_job_spec_template_spec_affinity_node_affinity_preference_match_expressions.py
dragonk8s/dragon/models/io_dragon_apps_v1_job_spec_template_spec_affinity_node_affinity_preferred_during_scheduling_ignored_during_execution.py
dragonk8s/dragon/models/io_dragon_apps_v1_job_spec_template_spec_affinity_node_affinity_required_during_scheduling_ignored_during_execution.py
dragonk8s/dragon/models/io_dragon_apps_v1_job_spec_template_spec_affinity_node_affinity_required_during_scheduling_ignored_during_execution_node_selector_terms.py
dragonk8s/dragon/models/io_dragon_apps_v1_job_spec_template_spec_affinity_pod_affinity.py
dragonk8s/dragon/models/io_dragon_apps_v1_job_spec_template_spec_affinity_pod_affinity_pod_affinity_term.py
dragonk8s/dragon/models/io_dragon_apps_v1_job_spec_template_spec_affinity_pod_affinity_pod_affinity_term_label_selector.py
dragonk8s-1.1.0.dist-info/METADATA
dragonk8s-1.1.0.dist-info/WHEEL
dragonk8s-1.1.0.dist-info/top_level.txt
dragonk8s-1.1.0.dist-info/RECORD
