Metadata-Version: 2.4
Name: dragonk8s
Version: 1.1.0
Summary: A k8s implement of Python3
Home-page: https://dragonk8s.com
Author: ma
Author-email: 591867837@qq.com
Requires-Dist: cachetools==5.2.0
Requires-Dist: certifi==2022.9.24
Requires-Dist: charset-normalizer==2.1.1
Requires-Dist: google-auth==2.14.1
Requires-Dist: idna==3.4
Requires-Dist: kubernetes==25.3.0
Requires-Dist: oauthlib==3.2.2
Requires-Dist: pyasn1==0.4.8
Requires-Dist: pyasn1-modules==0.2.8
Requires-Dist: python-dateutil==2.8.2
Requires-Dist: pytz==2022.7
Requires-Dist: PyYAML==6.0.2
Requires-Dist: requests==2.28.1
Requires-Dist: requests-oauthlib==1.3.1
Requires-Dist: rsa==4.9
Requires-Dist: six==1.16.0
Requires-Dist: urllib3==1.26.13
Requires-Dist: websocket-client==1.4.2
Dynamic: author
Dynamic: author-email
Dynamic: home-page
Dynamic: requires-dist
Dynamic: summary
